MANIFEST.in
README.txt
setup.py
collective/__init__.py
collective.js.underscore.egg-info/PKG-INFO
collective.js.underscore.egg-info/SOURCES.txt
collective.js.underscore.egg-info/dependency_links.txt
collective.js.underscore.egg-info/entry_points.txt
collective.js.underscore.egg-info/namespace_packages.txt
collective.js.underscore.egg-info/not-zip-safe
collective.js.underscore.egg-info/requires.txt
collective.js.underscore.egg-info/top_level.txt
collective/js/__init__.py
collective/js/underscore/__init__.py
collective/js/underscore/configure.zcml
collective/js/underscore/tests.py
collective/js/underscore/profiles/default/jsregistry.xml
collective/js/underscore/profiles/default/metadata.xml
collective/js/underscore/resources/underscore.min.js
docs/HISTORY.txt
docs/LICENSE.MIT