Metadata-Version: 1.1
Name: collective.js.underscore
Version: 1.5.0
Summary: underscore.js for plone
Home-page: https://github.com/collective/collective.js.underscore
Author: Denis Krienbuehl
Author-email: denis.krienbuehl@gmail.com
License: MIT
Keywords: javascript plone underscore
Platform: UNKNOWN
Classifier: Framework :: Plone
Classifier: Programming Language :: Python
Classifier: Intended Audience :: Developers
Classifier: License :: OSI Approved :: MIT License
